warlock/__init__.py
warlock/core.py
warlock/exceptions.py
warlock/model.py
warlock-2.0.0.dist-info/LICENSE
warlock-2.0.0.dist-info/WHEEL
warlock-2.0.0.dist-info/METADATA
warlock-2.0.0.dist-info/RECORD
