Metadata-Version: 2.1
Name: warlock
Version: 2.0.0
Summary: Python object model built on JSON schema and JSON patch.
Home-page: http://github.com/bcwaldon/warlock
License: Apache-2.0
Keywords: JSON schema,JSON patch,model validation
Author: Brian Waldon
Author-email: bcwaldon@gmail.com
Maintainer: Jan Willhaus
Maintainer-email: mail@janwillhaus.de
Requires-Python: >=3.7,<4.0
Classifier: Development Status :: 5 - Production/Stable
Classifier: Intended Audience :: Developers
Classifier: License :: OSI Approved :: Apache Software License
Classifier: Operating System :: MacOS :: MacOS X
Classifier: Operating System :: Microsoft :: Windows
Classifier: Operating System :: POSIX
Classifier: Programming Language :: Python
Classifier: Programming Language :: Python :: 3
Classifier: Programming Language :: Python :: 3.10
Classifier: Programming Language :: Python :: 3.7
Classifier: Programming Language :: Python :: 3.8
Classifier: Programming Language :: Python :: 3.9
Classifier: Topic :: Software Development :: Libraries :: Python Modules
Requires-Dist: jsonpatch (>=1,<2)
Requires-Dist: jsonschema (>=4,<5)
Project-URL: Repository, http://github.com/bcwaldon/warlock
